pdgrid/__init__.py
pdgrid/aggrid.py
pdgrid/pdgrid.py
pdgrid-0.1.3.dist-info/METADATA
pdgrid-0.1.3.dist-info/WHEEL
pdgrid-0.1.3.dist-info/top_level.txt
pdgrid-0.1.3.dist-info/RECORD
