Metadata-Version: 2.1
Name: pdgrid
Version: 0.1.3
Summary: An interface to pandas for grid data server.
Home-page: https://github.com/slindal/pdgrid
Author: Svein Lindal
Author-email: svein.lindal@gmail.com
License: UNKNOWN
Project-URL: Bug Tracker, https://github.com/slindal/pdgrid/issues
Platform: UNKNOWN
Classifier: Programming Language :: Python :: 3
Classifier: License :: OSI Approved :: MIT License
Classifier: Operating System :: OS Independent
Requires-Python: <3.10,>=3.8
Requires-Dist: pandas
